cgui/__init__.py
open_console_gui-0.32.dist-info/METADATA
open_console_gui-0.32.dist-info/WHEEL
open_console_gui-0.32.dist-info/top_level.txt
open_console_gui-0.32.dist-info/RECORD
