Metadata-Version: 2.1
Name: open-console-gui
Version: 0.32
Summary: ✧ Interactive Console Menus & Loading Bars ✧
Author: SHARKstudio (Jay Morrington)
Author-email: <animating.du.38@gmail.com>
Keywords: python,menu,progress-bar,gui,terminal,console
Classifier: Intended Audience :: Developers
Classifier: Operating System :: Unix
Classifier: Operating System :: MacOS :: MacOS X
Classifier: Operating System :: Microsoft :: Windows
Requires-Dist: keyboard
